Metadata-Version: 2.1
Name: clumpi
Version: 1.0.1
Summary: Calculate Clumpiness index by Zhang, Bradlow and Small (2015)
Home-page: https://jun-systems.info
Download-URL: https://github.com/jniimi/clumpi
Author: jniimi
Author-email: jniimi@meijo-u.ac.jp
License: MIT
Keywords: RFMC Clumpiness marketing CRM
License-File: LICENSE
